Comparison/Compare_4.v
//		
//	Magnitude Comparator, 4 bit.
//	
//	port		:	a 		: in	: term 
//				:	b		: in	: term
//				:	gt		: out	: 1 if a > b
//				:	lt		: out	: 1 if a < b
//				:	eq		: out	: 1 if a == b
//


module Compare_4(a, b, gt, lt, eq);

	input [3:0] a, b;
	
	output gt, lt, eq;
	
	assign gt = a > b;
	assign lt = a < b;
	assign eq = ~(gt | lt);
	
endmodule

Comparison/TB/Compare_4_tb.v
// Comparator Test Bench 4 bit
// Harith Manoj (C) 2021

module Compare_4_tb;

	reg [3:0] a, b;
	wire gt, lt, eq;
	
	Compare_4 compare4Bit(.a(a), .b(b), .gt(gt), .lt(lt), .eq(eq));
	
	initial begin
	
		$dumpfile("Compare_4_tb.vcd");
		$dumpvars(2, Compare_4_tb);
		
		#2 	a = 4'd14;
			b = 4'd10;
		#2 	a = 4'd8;
			b = 4'd9;
		#2 	a = 4'd1;
			b = 4'd6;
		#2 	a = 4'd7;
			b = 4'd12;
		#2 	a = 4'd9;
			b = 4'd2;
		#2 	a = 4'd15;
			b = 4'd3;
		#2	a = 4'd10;
			b = 4'd10;
		#2	$finish;
	end
	
	initial
		$monitor( " a ( %1h : %2d ) <=> b ( %1h : %2d ) | Greater? : %1b ; Lesser? : %1b ; Equal? : %1b",
			a, a, b, b, gt, lt, eq);
			
	

endmodule

Comparison/build/Compare_4_tb.vcd
$date
	Sat May 15 22:27:34 2021
$end
$version
	Icarus Verilog
$end
$timescale
	1s
$end
$scope module Compare_4_tb $end
$var wire 1 ! lt $end
$var wire 1 " gt $end
$var wire 1 # eq $end
$var reg 4 $ a [3:0] $end
$var reg 4 % b [3:0] $end
$scope module compare4Bit $end
$var wire 4 & a [3:0] $end
$var wire 4 ' b [3:0] $end
$var wire 1 # eq $end
$var wire 1 ! lt $end
$var wire 1 " gt $end
$upscope $end
$upscope $end
$enddefinitions $end
#0
$dumpvars
bx '
bx &
bx %
bx $
x#
x"
x!
$end
#2
0#
1"
0!
b1010 %
b1010 '
b1110 $
b1110 &
#4
b1001 %
b1001 '
0"
1!
b1000 $
b1000 &
#6
b110 %
b110 '
b1 $
b1 &
#8
b1100 %
b1100 '
0"
1!
b111 $
b111 &
#10
1"
0!
b10 %
b10 '
b1001 $
b1001 &
#12
b11 %
b11 '
b1111 $
b1111 &
#14
1#
0"
b1010 %
b1010 '
b1010 $
b1010 &
