Convertors/BcdSevenSegment.v
//		Converts BCD to seven segment display control signals
//
//		Port	: enable	: in	: enable connection.
//				: bcd		: in	: bcd input.
//				: a -- g	: out 	: output control signals.
//				: AA		: out	: anode enable
//	
//			


module BcdSevenSegment 
	( n_enable, bcd, a, b, c, d, e, f, g, AA);
	
	input n_enable;
	input [3:0] bcd;
	
	output wire a, b, c, d, e, f, g, AA;
	
	reg [6:0] out;
	
	always@(bcd or n_enable) begin
		
		case(bcd)
			4'h0: 		out = 7'b0000001;
			4'h1: 		out = 7'b1001111;
			4'h2: 		out = 7'b0010010;
			4'h3: 		out = 7'b0000110;
			4'h4: 		out = 7'b1001100;
			4'h5: 		out = 7'b0100100;
			4'h6: 		out = 7'b0100000;
			4'h7:		out = 7'b0001111;
			4'h8: 		out = 7'b0000000;
			4'h9: 		out = 7'b0000100;
			default: 	out = 7'b0000001;
		endcase
		
	end
	
	assign AA = ~n_enable;
	
	assign a = out[6] | n_enable;
	assign b = out[5] | n_enable;
	assign c = out[4] | n_enable;
	assign d = out[3] | n_enable;
	assign e = out[2] | n_enable;
	assign f = out[1] | n_enable;
	assign g = out[0] | n_enable;
	
endmodule

Convertors/TB/BcdSevenSegment_tb.v
// BCD to Seven Segment convertor test bench


module BcdSevenSegment_tb;

	wire a, b, c, d, e, f, g, AA;

	reg n_enable;
	reg [3:0] bcd;
	reg clk;
	BcdSevenSegment bcdconv( .n_enable(n_enable), .bcd(bcd), .a(a), .b(b), .c(c), .d(d), .e(e), .f(f), .g(g), .AA(AA));
	
	initial begin
		$dumpfile("BcdSevenSegment_tb.vcd");
		$dumpvars(2, BcdSevenSegment_tb);
		
		n_enable = 0;
		bcd = 4'b1111;
		clk = 0;
		
		#30 $finish;
	end
	
	always #2 clk = ~clk;
	
	always @(clk) begin
		if(bcd == 4'b1001) begin
			n_enable = ~n_enable;
			bcd = 4'b1111;
		end
		
		bcd = bcd + 1;
		
	end
	
	initial
		$monitor("    %4b not enable %1b AA %1b =>\n      %1b \n     %1b %1b \n      %1b \n     %1b %1b \n      %1b\n",
					bcd, n_enable, AA, a, f, b, g, e, c, d);
endmodule

Convertors/build/BcdSevenSegment_tb.vcd
$date
	Sun May 16 19:01:20 2021
$end
$version
	Icarus Verilog
$end
$timescale
	1s
$end
$scope module BcdSevenSegment_tb $end
$var wire 1 ! g $end
$var wire 1 " f $end
$var wire 1 # e $end
$var wire 1 $ d $end
$var wire 1 % c $end
$var wire 1 & b $end
$var wire 1 ' a $end
$var wire 1 ( AA $end
$var reg 4 ) bcd [3:0] $end
$var reg 1 * clk $end
$var reg 1 + n_enable $end
$scope module bcdconv $end
$var wire 1 ( AA $end
$var wire 1 ' a $end
$var wire 1 & b $end
$var wire 4 , bcd [3:0] $end
$var wire 1 % c $end
$var wire 1 $ d $end
$var wire 1 # e $end
$var wire 1 " f $end
$var wire 1 ! g $end
$var wire 1 + n_enable $end
$var reg 7 - out [6:0] $end
$upscope $end
$upscope $end
$enddefinitions $end
#0
$dumpvars
b1 -
b0 ,
0+
0*
b0 )
1(
0'
0&
0%
0$
0#
0"
1!
$end
#2
1'
1$
1#
1"
b1001111 -
b1 )
b1 ,
1*
#4
0'
1%
0$
0#
0!
b10010 -
b10 )
b10 ,
0*
#6
0%
1#
b110 -
b11 )
b11 ,
1*
#8
1'
1$
0"
b1001100 -
b100 )
b100 ,
0*
#10
0'
1&
0$
b100100 -
b101 )
b101 ,
1*
#12
0#
b100000 -
b110 )
b110 ,
0*
#14
0&
1$
1#
1"
1!
b1111 -
b111 )
b111 ,
1*
#16
0$
0#
0"
0!
b0 -
b1000 )
b1000 ,
0*
#18
1#
b100 -
b1001 )
b1001 ,
1*
#20
0(
1'
1&
1%
1$
1"
1!
b1 -
b0 )
b0 ,
1+
0*
#22
b1001111 -
b1 )
b1 ,
1*
#24
b10010 -
b10 )
b10 ,
0*
#26
b110 -
b11 )
b11 ,
1*
#28
b1001100 -
b100 )
b100 ,
0*
#30
b100100 -
b101 )
b101 ,
1*
