mux/Mux2_1Gate.v
//		2:1 Mux created using gate level modeling
//		
//		Ports	:	d0	: in	: 1st input, selected if sel is 0
//				:	d1	: in	: 2nd input, selected if sel is 1
//				:	sel	: in	: selection bit.
//				:	out : out 	: selected output
//
//		Harith Manoj (C) 2021



module Mux2_1Gate( d0, d1, sel, out);

	input d0, d1, sel;
	
	output out;
	
	wire min0, min1, nSel;
	
	not (nSel, sel);
	
	and term0(min0, d0, nSel);
	and term1(min1, d1, sel);
	
	or (out, min0, min1);
	
endmodule

mux/Mux2_1DataFlow.v
//		2:1 Mux created using data flow modeling
//		
//		Ports	:	d0	: in	: 1st input, selected if sel is 0
//				:	d1	: in	: 2nd input, selected if sel is 1
//				:	sel	: in	: selection bit.
//				:	out : out 	: selected output
//
//		Harith Manoj (C) 2021



module Mux2_1DataFlow( d0, d1, sel, out);

	input d0, d1, sel;
	
	output out;
	
	assign out = sel ? d1 : d0;
	
endmodule

mux/Mux2_1Behavioral.v
//		2:1 Mux created using Behavioral modeling
//		
//		Ports	:	d0	: in	: 1st input, selected if sel is 0
//				:	d1	: in	: 2nd input, selected if sel is 1
//				:	sel	: in	: selection bit.
//				:	out : out 	: selected output
//
//
//		Harith Manoj (C) 2021



module Mux2_1Behavioral( d0, d1, sel, out);

	input d0, d1, sel;
	
	output reg out;
	
	always @(d0 or d1 or sel) begin
		
		if(sel) 
			out = d1;
		else
			out = d0;
			
	end
	
endmodule

mux/TB/mux2_1_tb.v
// Test Bench for muxs
//		Harith Manoj (C) 2021


module mux2_1_tb;
	
	reg [2:0] in;
	
	assign d0 = in[2];
	assign d1 = in[1];
	assign sel = in[0];
	
	wire outGate, outBehavioural, outDataFlow;
	
	Mux2_1Behavioral Behavioral(.d0(d0), .d1(d1), .sel(sel), .out(outBehavioural));
	Mux2_1DataFlow DataFlow(.d0(d0), .d1(d1), .sel(sel), .out(outDataFlow));
	Mux2_1Gate Gate(.d0(d0), .d1(d1), .sel(sel), .out(outGate));
	
	initial begin
		
		$dumpfile("mux2_1_tb.vcd");
		$dumpvars(2, mux2_1_tb);
		
		#2 in = 3'd0;
		#2 in = 3'd1;
		#2 in = 3'd2;
		#2 in = 3'd3;
		#2 in = 3'd4;
		#2 in = 3'd5;
		#2 in = 3'd6;
		#2 in = 3'd7;
		#2 $finish;
	
	end
	
	initial 
		$monitor( "time: %t ; d0 = %1b; d1 = %1b; sel = %1b; out gate = %1b; out beh = %1b; out data = %1b;",
					$time, d0, d1, sel, outGate, outBehavioural, outDataFlow);
					
	
endmodule

mux/build/mux2_1_tb.vcd
$date
	Sat May 15 22:43:11 2021
$end
$version
	Icarus Verilog
$end
$timescale
	1s
$end
$scope module mux2_1_tb $end
$var wire 1 ! sel $end
$var wire 1 " outGate $end
$var wire 1 # outDataFlow $end
$var wire 1 $ outBehavioural $end
$var wire 1 % d1 $end
$var wire 1 & d0 $end
$var reg 3 ' in [2:0] $end
$scope module Behavioral $end
$var wire 1 & d0 $end
$var wire 1 % d1 $end
$var wire 1 ! sel $end
$var reg 1 $ out $end
$upscope $end
$scope module DataFlow $end
$var wire 1 & d0 $end
$var wire 1 % d1 $end
$var wire 1 ! sel $end
$var wire 1 # out $end
$upscope $end
$scope module Gate $end
$var wire 1 & d0 $end
$var wire 1 % d1 $end
$var wire 1 ( min0 $end
$var wire 1 ) min1 $end
$var wire 1 * nSel $end
$var wire 1 " out $end
$var wire 1 ! sel $end
$upscope $end
$upscope $end
$enddefinitions $end
#0
$dumpvars
x*
x)
x(
bx '
x&
x%
x$
x#
x"
x!
$end
#2
0"
0(
0$
0#
1*
0)
0&
0%
0!
b0 '
#4
0*
1!
b1 '
#6
1*
1%
0!
b10 '
#8
1"
1$
1#
0*
1)
1!
b11 '
#10
1(
1*
0)
1&
0%
0!
b100 '
#12
0"
0(
0$
0#
0*
1!
b101 '
#14
1"
1(
1$
1#
1*
1%
0!
b110 '
#16
0(
0*
1)
1!
b111 '
