mux/Mux2_1_2Behavioral.v
//		2 bit 2:1 Mux created using Behavioral modeling
//		
//		Ports	:	d0	: in	: 1st input, selected if sel is 0
//				:	d1	: in	: 2nd input, selected if sel is 1
//				:	sel	: in	: selection bit.
//				:	out : out 	: selected output
//
//		Harith Manoj (C) 2021



module Mux2_1Behavioral( d0, d1, sel, out);

	input [1:0] d0, d1;
	input sel;
	
	output reg [1:0] out;
	
	always @(d0 or d1 or sel) begin
		
		if(sel) 
			out = d1;
		else
			out = d0;
			
	end
	
endmodule

mux/Mux3_1Behavioral.v
//		3:1 Mux created using multiple 2:1 Mux Behavioral modeling
//		
//		Ports	:	d0	: in	: 1st input, selected if sel is 00
//				:	d1	: in	: 2nd input, selected if sel is 01
//				:	d2	: in	: 3rd input, selectes if sel is 10 or 11
//				:	sel	: in	: selection bits.
//				:	out : out 	: selected output
//
//		Harith Manoj (C) 2021



module Mux3_1Behavioral( d0, d1, d2, sel, out);

	input d0, d1, d2;
	input [1:0] sel;
	
	output wire out;
	
	wire lowerSelect;
	
	Mux2_1Behavioral lowerMux(.d0(d0), .d1(d1), .sel(sel[0]), .out(lowerSelect));
	Mux2_1Behavioral upperMux(.d0(lowerSelect), .d1(d2), .sel(sel[1]), .out(out));
	
endmodule

mux/TB/mux3_1_tb.v
// Test bench for 3-1 mux
// Harith Manoj (C) 2021

module mux3_1_tb;

	reg [4:0] in;
	
	initial
		in = 4'b0000;
	
	assign d0 = in[4];
	assign d1 = in[3];
	assign d2 = in[2];
	wire [1:0] sel;
	assign sel = in[1:0];
	wire out;
	
	
	Mux3_1Behavioral muxBeh3_1 (.d0(d0), .d1(d1), .d2(d2), .sel(sel), .out(out));
	
	always #2 in = in + 1;
	
	initial begin
		$dumpfile("mux3_1_tb.vcd");
		$dumpvars(2, mux3_1_tb);
		#80 $finish;
		
	end
		
	initial 
		$monitor("time : %t ; d[0:1:2] = %1b %1b %1b ; sel = %2b ; out = %1b ",
				$time, d0, d1, d2, sel, out);

endmodule

mux/build/mux3_1_tb.vcd
$date
	Sun May 16 18:22:48 2021
$end
$version
	Icarus Verilog
$end
$timescale
	1s
$end
$scope module mux3_1_tb $end
$var wire 2 ! sel [1:0] $end
$var wire 1 " out $end
$var wire 1 # d2 $end
$var wire 1 $ d1 $end
$var wire 1 % d0 $end
$var reg 5 & in [4:0] $end
$scope module muxBeh3_1 $end
$var wire 1 % d0 $end
$var wire 1 $ d1 $end
$var wire 1 # d2 $end
$var wire 2 ' sel [1:0] $end
$var wire 1 " out $end
$var wire 1 ( lowerSelect $end
$upscope $end
$upscope $end
$enddefinitions $end
#0
$dumpvars
0(
b0 '
b0 &
0%
0$
0#
0"
b0 !
$end
#2
b1 !
b1 '
b1 &
#4
b10 !
b10 '
b10 &
#6
b11 !
b11 '
b11 &
#8
1#
b0 !
b0 '
b100 &
#10
b1 !
b1 '
b101 &
#12
1"
b10 !
b10 '
b110 &
#14
b11 !
b11 '
b111 &
#16
0"
1$
0#
b0 !
b0 '
b1000 &
#18
1"
1(
b1 !
b1 '
b1001 &
#20
0(
0"
b10 !
b10 '
b1010 &
#22
1(
b11 !
b11 '
b1011 &
#24
0(
0"
1#
b0 !
b0 '
b1100 &
#26
1"
1(
b1 !
b1 '
b1101 &
#28
0(
b10 !
b10 '
b1110 &
#30
1(
b11 !
b11 '
b1111 &
#32
1%
0$
0#
b0 !
b0 '
b10000 &
#34
0"
0(
b1 !
b1 '
b10001 &
#36
1(
b10 !
b10 '
b10010 &
#38
0(
b11 !
b11 '
b10011 &
#40
1"
1(
1#
b0 !
b0 '
b10100 &
#42
0"
0(
b1 !
b1 '
b10101 &
#44
1(
1"
b10 !
b10 '
b10110 &
#46
0(
b11 !
b11 '
b10111 &
#48
1(
1"
1$
0#
b0 !
b0 '
b11000 &
#50
b1 !
b1 '
b11001 &
#52
0"
b10 !
b10 '
b11010 &
#54
b11 !
b11 '
b11011 &
#56
1"
1#
b0 !
b0 '
b11100 &
#58
b1 !
b1 '
b11101 &
#60
b10 !
b10 '
b11110 &
#62
b11 !
b11 '
b11111 &
#64
0"
0(
0%
0$
0#
b0 !
b0 '
b0 &
#66
b1 !
b1 '
b1 &
#68
b10 !
b10 '
b10 &
#70
b11 !
b11 '
b11 &
#72
1#
b0 !
b0 '
b100 &
#74
b1 !
b1 '
b101 &
#76
1"
b10 !
b10 '
b110 &
#78
b11 !
b11 '
b111 &
#80
0"
1$
0#
b0 !
b0 '
b1000 &
