mux/Mux2_1Gate.v
//		2:1 Mux created using gate level modeling
//		
//		Ports	:	d0	: in	: 1st input, selected if sel is 0
//				:	d1	: in	: 2nd input, selected if sel is 1
//				:	sel	: in	: selection bit.
//				:	out : out 	: selected output
//
//		Harith Manoj (C) 2021



module Mux2_1Gate( d0, d1, sel, out);

	input d0, d1, sel;
	
	output out;
	
	wire min0, min1, nSel;
	
	not (nSel, sel);
	
	and term0(min0, d0, nSel);
	and term1(min1, d1, sel);
	
	or (out, min0, min1);
	
endmodule

mux/Mux2_1DataFlow.v
//		2:1 Mux created using data flow modeling
//		
//		Ports	:	d0	: in	: 1st input, selected if sel is 0
//				:	d1	: in	: 2nd input, selected if sel is 1
//				:	sel	: in	: selection bit.
//				:	out : out 	: selected output
//
//		Harith Manoj (C) 2021



module Mux2_1DataFlow( d0, d1, sel, out);

	input d0, d1, sel;
	
	output out;
	
	assign out = sel ? d1 : d0;
	
endmodule

mux/Mux2_1Behavioral.v
//		2:1 Mux created using Behavioral modeling
//		
//		Ports	:	d0	: in	: 1st input, selected if sel is 0
//				:	d1	: in	: 2nd input, selected if sel is 1
//				:	sel	: in	: selection bit.
//				:	out : out 	: selected output
//
//
//		Harith Manoj (C) 2021



module Mux2_1Behavioral( d0, d1, sel, out);

	input d0, d1, sel;
	
	output reg out;
	
	always @(d0 or d1 or sel) begin
		
		if(sel) 
			out = d1;
		else
			out = d0;
			
	end
	
endmodule

mux/Mux2_1_2Gate.v
//		2bit 2:1 Mux created using gate level modeling
//		
//		Ports	:	d0	: in	: 1st input, selected if sel is 0
//				:	d1	: in	: 2nd input, selected if sel is 1
//				:	sel	: in	: selection bit.
//				:	out : out 	: selected output
//
//		Harith Manoj (C) 2021



module Mux2_1_2Gate( d0, d1, sel, out);

	input[1:0] d0, d1;
	input sel;
	
	output [1:0] out;
	
	wire [1:0] min0, min1;
	wire nSel;
	
	not (nSel, sel);
	
	and term00(min0[0], d0[0], nSel);
	and term01(min0[1], d0[1], nSel);
	
	and term10(min1[0], d1[0], sel);
	and term11(min1[1], d1[1], sel);
	
	or ar0(out[0], min0[0], min1[0]);
	or ar1(out[1], min0[1], min1[1]);
	
endmodule

mux/TB/mux_tb.v
// Test Bench for muxs
//		Harith Manoj (C) 2021


module mux_tb;
	
	reg [4:0] in;
	
	assign a = in[4];
	assign a1 = in[3];
	assign b = in[2];
	assign b1 = in[1];
	assign s = in[0];
	
	wire outgt, outbh, outData;
	wire [1:0] out2gt;
	
	Mux2_1_2Gate Gate2Bit(.d0(in[4:3]), .d1(in[2:1]), .sel(s), .out(out2gt));
	Mux2_1Behavioral Behavioral(.d0(a), .d1(b), .sel(s), .out(outbh));
	Mux2_1DataFlow DataFlow(.d0(a), .d1(b), .sel(s), .out(outData));
	Mux2_1Gate Gate(.d0(a), .d1(b), .sel(s), .out(outgt));
	
	initial begin
		
		$dumpfile("mux_tb.vcd");
		$dumpvars(2, mux_tb);
		
		#2 in = 5'd0;
		#2 in = 5'd1;
		#2 in = 5'd2;
		#2 in = 5'd3;
		#2 in = 5'd4;
		#2 in = 5'd5;
		#2 in = 5'd6;
		#2 in = 5'd7;
		#2 in = 5'd8;
		#2 in = 5'd9;
		#2 in = 5'd10;
		#2 in = 5'd11;
		#2 in = 5'd12;
		#2 in = 5'd13;
		#2 in = 5'd14;
		#2 in = 5'd15;
		#2 in = 5'd16;
		#2 in = 5'd17;
		#2 in = 5'd18;
		#2 in = 5'd19;
		#2 in = 5'd20;
		#2 in = 5'd21;
		#2 in = 5'd22;
		#2 in = 5'd23;
		#2 in = 5'd24;
		#2 in = 5'd25;
		#2 in = 5'd26;
		#2 in = 5'd27;
		#2 in = 5'd28;
		#2 in = 5'd29;
		#2 in = 5'd30;
		#2 in = 5'd31;
		#2 $finish;
	
	end
	
	initial 
		$monitor( "time: %t ; a = %1b; b = %1b; s = %1b; a[2] = %2b; b[2] = %2b; out 2 gate = %2b; out gate = %1b; out beh = %1b; out data = %1b;",
					$time, a, b, s, in[4:3], in[2:1], out2gt, outgt, outbh, outData);
					
	
endmodule

mux/build/mux_tb.vcd
$date
	Sat May 15 22:44:00 2021
$end
$version
	Icarus Verilog
$end
$timescale
	1s
$end
$scope module mux_tb $end
$var wire 1 ! s $end
$var wire 1 " outgt $end
$var wire 1 # outbh $end
$var wire 1 $ outData $end
$var wire 2 % out2gt [1:0] $end
$var wire 1 & b1 $end
$var wire 1 ' b $end
$var wire 1 ( a1 $end
$var wire 1 ) a $end
$var reg 5 * in [4:0] $end
$scope module Behavioral $end
$var wire 1 ) d0 $end
$var wire 1 ' d1 $end
$var wire 1 ! sel $end
$var reg 1 # out $end
$upscope $end
$scope module DataFlow $end
$var wire 1 ) d0 $end
$var wire 1 ' d1 $end
$var wire 1 ! sel $end
$var wire 1 $ out $end
$upscope $end
$scope module Gate $end
$var wire 1 ) d0 $end
$var wire 1 ' d1 $end
$var wire 1 + min0 $end
$var wire 1 , min1 $end
$var wire 1 - nSel $end
$var wire 1 " out $end
$var wire 1 ! sel $end
$upscope $end
$scope module Gate2Bit $end
$var wire 2 . d0 [1:0] $end
$var wire 2 / d1 [1:0] $end
$var wire 1 0 nSel $end
$var wire 1 ! sel $end
$var wire 2 1 out [1:0] $end
$var wire 2 2 min1 [1:0] $end
$var wire 2 3 min0 [1:0] $end
$upscope $end
$upscope $end
$enddefinitions $end
#0
$dumpvars
bx 3
bx 2
bx 1
x0
bx /
bx .
x-
x,
x+
bx *
x)
x(
x'
x&
bx %
x$
x#
x"
x!
$end
#2
b0 %
b0 1
0"
b0 3
0+
0#
0$
1-
0,
10
b0 2
0)
0(
0'
0&
0!
b0 .
b0 /
b0 *
#4
0-
00
1!
b1 *
#6
1-
10
1&
0!
b1 /
b10 *
#8
b1 %
b1 1
0-
00
b1 2
1!
b11 *
#10
b0 %
b0 1
1-
10
b0 2
1'
0&
0!
b10 /
b100 *
#12
b10 %
b10 1
1"
1#
1$
0-
1,
00
b10 2
1!
b101 *
#14
b0 %
b0 1
0"
0#
0$
1-
0,
10
b0 2
1&
0!
b11 /
b110 *
#16
b11 %
b11 1
1"
1#
1$
0-
1,
00
b11 2
1!
b111 *
#18
b1 %
b1 1
0"
b1 3
0#
0$
1-
0,
10
b0 2
1(
0'
0&
0!
b1 .
b0 /
b1000 *
#20
b0 %
b0 1
b0 3
0-
00
1!
b1001 *
#22
b1 %
b1 1
b1 3
1-
10
1&
0!
b1 /
b1010 *
#24
b0 3
0-
00
b1 2
1!
b1011 *
#26
b1 %
b1 1
b1 3
1-
10
b0 2
1'
0&
0!
b10 /
b1100 *
#28
b10 %
b10 1
1"
b0 3
1#
1$
0-
1,
00
b10 2
1!
b1101 *
#30
b1 %
b1 1
0"
b1 3
0#
0$
1-
0,
10
b0 2
1&
0!
b11 /
b1110 *
#32
b11 %
b11 1
1"
b0 3
1#
1$
0-
1,
00
b11 2
1!
b1111 *
#34
b10 %
b10 1
b10 3
1+
1-
0,
10
b0 2
1)
0(
0'
0&
0!
b10 .
b0 /
b10000 *
#36
b0 %
b0 1
0"
0+
b0 3
0#
0$
0-
00
1!
b10001 *
#38
b10 %
b10 1
1"
1+
b10 3
1#
1$
1-
10
1&
0!
b1 /
b10010 *
#40
0"
b1 %
b1 1
0+
b0 3
0#
0$
0-
00
b1 2
1!
b10011 *
#42
1"
b10 %
b10 1
1+
b10 3
1#
1$
1-
10
b0 2
1'
0&
0!
b10 /
b10100 *
#44
0+
b0 3
0-
1,
00
b10 2
1!
b10101 *
#46
b10 %
b10 1
1+
1"
b10 3
1-
0,
10
b0 2
1&
0!
b11 /
b10110 *
#48
b11 %
b11 1
0+
b0 3
0-
1,
00
b11 2
1!
b10111 *
#50
b11 %
b11 1
1+
1"
b11 3
1-
0,
10
b0 2
1(
0'
0&
0!
b11 .
b0 /
b11000 *
#52
b0 %
b0 1
0"
0+
b0 3
0#
0$
0-
00
1!
b11001 *
#54
b11 %
b11 1
1"
1+
b11 3
1#
1$
1-
10
1&
0!
b1 /
b11010 *
#56
b1 %
b1 1
0"
0+
b0 3
0#
0$
0-
00
b1 2
1!
b11011 *
#58
1"
b11 %
b11 1
1+
b11 3
1#
1$
1-
10
b0 2
1'
0&
0!
b10 /
b11100 *
#60
b10 %
b10 1
0+
b0 3
0-
1,
00
b10 2
1!
b11101 *
#62
b11 %
b11 1
1+
1"
b11 3
1-
0,
10
b0 2
1&
0!
b11 /
b11110 *
#64
0+
b0 3
0-
1,
00
b11 2
1!
b11111 *
