fsm/fsm001.v
// Finite State Machine which follows State Diagram : 
//
//		000 -----> 001 -----> 011 -----> 101 -----> 111 -----> 010
//       ^                                                      |
//	     |                                                      |
//       +------------------------------------------------------+
//
//		Has synchronous reset, 
//		Port	: clk		: in	: Synchronous clock
//				: n_reset	: in	: Resets fsm to 000
//				: in    	: in	: change state to next if 1 else remains same.
//				: Q			: out	: Output of fsm
//				
//		

module fsm001( clk, n_reset, in, Q);

	input clk, n_reset, in;
	output reg [2:0] Q;
	
	initial
		Q = 3'b000;
		
	always@(posedge clk or in) begin
		
		if( !n_reset)
			Q = 3'b000;
		else if(in)
			case(Q)
				3'b000 : Q = 3'b001;
				3'b001 : Q = 3'b011;
				3'b011 : Q = 3'b101;
				3'b101 : Q = 3'b111;
				3'b111 : Q = 3'b010;
				3'b010 : Q = 3'b000;
				default: Q = 3'b000;
			endcase
	end
	
endmodule

fsm/tb/fsm001_tb.v
// fsm001 Test Bench
//	

module fsm001_tb;

	reg clk, n_reset, in;
	
	wire [2:0] Q;
	
	fsm001 fsm(.clk(clk), .n_reset(n_reset), .in(in), .Q(Q));
	
	always #0.5 clk = ~clk;
	
	
	initial begin
		
		$dumpfile("fsm001_tb.vcd");
		$dumpvars(2, fsm001_tb);
		
		clk = 0;
		in = 1;
		n_reset = 1;
		
		#30   n_reset= 0;
		#2	  in = 0;
		#1	  n_reset = 1;
		#10   in = 1;
		#10	  $finish;
		
	end
	
	initial
		$monitor("time : %t |  clk %1b | in %1b | n_reset %1b | Q %4b |", $time, clk, in, n_reset, Q);
		
endmodule

fsm/build/fsm001_tb.vcd
$date
	Sun May 16 21:20:08 2021
$end
$version
	Icarus Verilog
$end
$timescale
	1s
$end
$scope module fsm001_tb $end
$var wire 3 ! Q [2:0] $end
$var reg 1 " clk $end
$var reg 1 # in $end
$var reg 1 $ n_reset $end
$scope module fsm $end
$var wire 1 " clk $end
$var wire 1 # in $end
$var wire 1 $ n_reset $end
$var reg 3 % Q [2:0] $end
$upscope $end
$upscope $end
$enddefinitions $end
#0
$dumpvars
b1 %
1$
1#
0"
b1 !
$end
#1
b11 !
b11 %
1"
#2
0"
#3
b101 !
b101 %
1"
#4
0"
#5
b111 !
b111 %
1"
#6
0"
#7
b10 !
b10 %
1"
#8
0"
#9
b0 !
b0 %
1"
#10
0"
#11
b1 !
b1 %
1"
#12
0"
#13
b11 !
b11 %
1"
#14
0"
#15
b101 !
b101 %
1"
#16
0"
#17
b111 !
b111 %
1"
#18
0"
#19
b10 !
b10 %
1"
#20
0"
#21
b0 !
b0 %
1"
#22
0"
#23
b1 !
b1 %
1"
#24
0"
#25
b11 !
b11 %
1"
#26
0"
#27
b101 !
b101 %
1"
#28
0"
#29
b111 !
b111 %
1"
#30
0"
0$
#31
b0 !
b0 %
1"
#32
0"
0#
#33
1"
1$
#34
0"
#35
1"
#36
0"
#37
1"
#38
0"
#39
1"
#40
0"
#41
1"
#42
0"
#43
b1 !
b1 %
1"
1#
#44
0"
#45
b11 !
b11 %
1"
#46
0"
#47
b101 !
b101 %
1"
#48
0"
#49
b111 !
b111 %
1"
#50
0"
#51
b10 !
b10 %
1"
#52
0"
#53
b0 !
b0 %
1"
