counter/CounterUpSyncBeh_4.v
//		4 bit up counter, synchronous reset; Behavioural
//		
//		Port	: clk		: in	: Synchronous clock
//				: reset		: in	: Resets counter to 0000
//				: enable	: in	: enable counting.
//				: Q			: out	: Output of counter
//				
//		Harith Manoj (C) 2021

module CounterUpSyncBeh_4 ( clk, n_reset, enable, Q );

	input clk, n_reset, enable;
	
	output reg [3:0] Q = 4'b0000;
	
	always @(posedge clk) begin
		if (!n_reset)
			Q <= 4'b0000;
		else if ( enable)
			Q <= Q + 1;
	end
	
endmodule

counter/TB/CounterUpSyncBeh_4_tb.v
// Counter Test Bench
//	Harith Manoj (C) 2021

module CounterUpSyncBeh_4_tb;

	reg clk, n_reset, enable;
	
	wire [3:0] Q;
	
	CounterUpSyncBeh_4 counterBeh(.clk(clk), .n_reset(n_reset), .enable(enable), .Q(Q));
	
	always #0.5 clk = ~clk;
	
	always #20 enable = ~enable;
	
	initial begin
		
		$dumpfile("CounterUpSyncBeh_4_tb.vcd");
		$dumpvars(2, CounterUpSyncBeh_4_tb);
		
		clk = 0;
		enable = 1;
		n_reset = 1;
		
		#25   n_reset= 0;
		
		#26	  n_reset = 1;
		
		#33	  $finish;
		
	end
	
	initial
		$monitor("time : %t |  clk %1b | enable %1b | n_reset %1b | Q %4b |", $time, clk, enable, n_reset, Q);
		
endmodule

counter/build/CounterUpSyncBeh_4_tb.vcd
$date
	Sun May 16 12:41:33 2021
$end
$version
	Icarus Verilog
$end
$timescale
	1s
$end
$scope module CounterUpSyncBeh_4_tb $end
$var wire 4 ! Q [3:0] $end
$var reg 1 " clk $end
$var reg 1 # enable $end
$var reg 1 $ n_reset $end
$scope module counterBeh $end
$var wire 1 " clk $end
$var wire 1 # enable $end
$var wire 1 $ n_reset $end
$var reg 4 % Q [3:0] $end
$upscope $end
$upscope $end
$enddefinitions $end
#0
$dumpvars
b0 %
1$
1#
0"
b0 !
$end
#1
b1 !
b1 %
1"
#2
0"
#3
b10 !
b10 %
1"
#4
0"
#5
b11 !
b11 %
1"
#6
0"
#7
b100 !
b100 %
1"
#8
0"
#9
b101 !
b101 %
1"
#10
0"
#11
b110 !
b110 %
1"
#12
0"
#13
b111 !
b111 %
1"
#14
0"
#15
b1000 !
b1000 %
1"
#16
0"
#17
b1001 !
b1001 %
1"
#18
0"
#19
b1010 !
b1010 %
1"
#20
0"
0#
#21
1"
#22
0"
#23
1"
#24
0"
#25
b0 !
b0 %
1"
0$
#26
0"
#27
1"
#28
0"
#29
1"
#30
0"
#31
1"
#32
0"
#33
1"
#34
0"
#35
1"
#36
0"
#37
1"
#38
0"
#39
1"
#40
0"
1#
#41
1"
#42
0"
#43
1"
#44
0"
#45
1"
#46
0"
#47
1"
#48
0"
#49
1"
#50
0"
#51
b1 !
b1 %
1"
1$
#52
0"
#53
b10 !
b10 %
1"
#54
0"
#55
b11 !
b11 %
1"
#56
0"
#57
b100 !
b100 %
1"
#58
0"
#59
b101 !
b101 %
1"
#60
0"
0#
#61
1"
#62
0"
#63
1"
#64
0"
#65
1"
#66
0"
#67
1"
#68
0"
#69
1"
#70
0"
#71
1"
#72
0"
#73
1"
#74
0"
#75
1"
#76
0"
#77
1"
#78
0"
#79
1"
#80
0"
1#
#81
b110 !
b110 %
1"
#82
0"
#83
b111 !
b111 %
1"
