adder/FullAdder_1.v
//		
//	Does 1 bit Addition.
//	
//	port		:	a 		: in	: augend 
//				:	b		: in	: addend 
//				:	cin		: in	: carry of last operation
//				:	cout	: out	: carry of this operation
//				:	sum		: out	: sum of a, b, cin
//
//		Harith Manoj (C) 2021


module FullAdder_1( a, b, cin, sum, cout);

	input a, b, cin;
	output sum, cout;
	
	assign sum = a ^ b ^ cin;
	assign cout = ( a&b) | (b & cin) | (a &cin);

endmodule;

adder/TB/FullAdder_1_tb.v
// Full Adder Test Bench 1 bit
// 

module FullAdder_1_tb;

	reg [2:0] in;
	
	assign a = in[2];
	assign b = in[1];
	assign cin = in[0];
	wire sum, cout;
	
	FullAdder_1 fullAdder1Bit(.a(a), .b(b), .cin(cin), .sum(sum), .cout(cout));
	
	initial begin
	
		$dumpfile("FullAdder_1_tb.vcd");
		$dumpvars(2, FullAdder_1_tb);
		
		#2 in = 3'd0;
		#2 in = 3'd1;
		#2 in = 3'd2;
		#2 in = 3'd3;
		#2 in = 3'd4;
		#2 in = 3'd5;
		#2 in = 3'd6;
		#2 in = 3'd7;
		#2 $finish;
	end
	
	initial
		$monitor( " a ( %1b ) + b ( %1b ) + cin ( %1b ) = sum ( %1b) + cout ( %1b )",
			a, b, cin, sum, cout);
			
	

endmodule

adder/build/FullAdder_1_tb.vcd
$date
	Sat May 15 22:21:00 2021
$end
$version
	Icarus Verilog
$end
$timescale
	1s
$end
$scope module FullAdder_1_tb $end
$var wire 1 ! sum $end
$var wire 1 " cout $end
$var wire 1 # cin $end
$var wire 1 $ b $end
$var wire 1 % a $end
$var reg 3 & in [2:0] $end
$scope module fullAdder1Bit $end
$var wire 1 % a $end
$var wire 1 $ b $end
$var wire 1 # cin $end
$var wire 1 " cout $end
$var wire 1 ! sum $end
$upscope $end
$upscope $end
$enddefinitions $end
#0
$dumpvars
bx &
x%
x$
x#
x"
x!
$end
#2
0"
0!
0%
0$
0#
b0 &
#4
1!
1#
b1 &
#6
1!
1$
0#
b10 &
#8
1"
0!
1#
b11 &
#10
0"
1!
1%
0$
0#
b100 &
#12
1"
0!
1#
b101 &
#14
1"
0!
1$
0#
b110 &
#16
1!
1#
b111 &
